patric_converte/__init__.py
patric_converte/converter.py
patric_converte-0.1.6.dist-info/entry_points.txt
patric_converte-0.1.6.dist-info/WHEEL
patric_converte-0.1.6.dist-info/METADATA
patric_converte-0.1.6.dist-info/RECORD
