Metadata-Version: 2.1
Name: patric-converte
Version: 0.1.6
Summary: 
Author: Patric Rocha
Author-email: patric_rocha@hotmail.com
Requires-Python: >=3.8,<4.0
Classifier: Programming Language :: Python :: 3
Classifier: Programming Language :: Python :: 3.10
Classifier: Programming Language :: Python :: 3.8
Classifier: Programming Language :: Python :: 3.9
Requires-Dist: black (>=21.12b0,<22.0)
Requires-Dist: click (>=8.0.3,<9.0.0)
Requires-Dist: flake8 (>=4.0.1,<5.0.0)
Requires-Dist: ipython (>=7.30.1,<8.0.0)
Requires-Dist: isort (>=5.10.1,<6.0.0)
Requires-Dist: mypy (>=0.910,<0.911)
